{"id":"u8ds0ev5gfoeqmyo2j4ga7y","title":"Pitfalls of Graph Neural Network Evaluation","desc":"","updated":1669501132295,"created":1669501132295,"custom":{},"fname":"zendron.import.title.pitfalls-of-graph-neural-network-evaluation","type":"note","vault":{"fsPath":".","selfContained":true,"name":"Zendron"},"contentHash":"9e7470a2e65da19ebd334cf56c088a81","links":[{"from":{"id":"lgs9kqn3iirui3exbo0y782","fname":"zendron.import.pitfalls-of-graph-neural-network-evaluation","vaultName":"Zendron"},"type":"backlink","position":{"start":{"line":3,"column":10,"offset":22},"end":{"line":3,"column":140,"offset":152},"indent":[]},"value":"zendron.import.title.pitfalls-of-graph-neural-network-evaluation","alias":"Pitfalls of Graph Neural Network Evaluation"}],"anchors":{},"children":[],"parent":"rgqsknpqcx55nvgkqekztfk","data":{}}
